celery_ranch/__init__.py
celery_ranch/task.py
celery_ranch/utils/__init__.py
celery_ranch/utils/backlog.py
celery_ranch/utils/lru_tracker.py
celery_ranch/utils/persistence.py
celery_ranch/utils/prioritize.py
celery_ranch-0.1.1.dist-info/licenses/LICENSE.md
celery_ranch-0.1.1.dist-info/METADATA
celery_ranch-0.1.1.dist-info/WHEEL
celery_ranch-0.1.1.dist-info/top_level.txt
celery_ranch-0.1.1.dist-info/RECORD
