Metadata-Version: 2.4
Name: celery-ranch
Version: 0.1.1
Summary: Celery Ranch: A Celery extension providing LRU-based task prioritization
Home-page: https://github.com/teleos-consulting/celery-ranch
Author: Matthew DesEnfants
Author-email: Matthew DesEnfants <matt@teleos.ltd>
License: MIT
Project-URL: Homepage, https://github.com/teleos-consulting/celery-ranch
Project-URL: Issues, https://github.com/teleos-consulting/celery-ranch/issues
Classifier: Development Status :: 3 - Alpha
Classifier: Intended Audience :: Developers
Classifier: License :: OSI Approved :: MIT License
Classifier: Programming Language :: Python :: 3
Classifier: Programming Language :: Python :: 3.8
Classifier: Programming Language :: Python :: 3.9
Classifier: Programming Language :: Python :: 3.10
Requires-Python: >=3.8
License-File: LICENSE.md
Requires-Dist: celery>=5.3.4
Provides-Extra: dev
Requires-Dist: pytest>=7.4.3; extra == "dev"
Requires-Dist: pytest-cov>=4.1.0; extra == "dev"
Requires-Dist: black>=23.11.0; extra == "dev"
Requires-Dist: isort>=5.12.0; extra == "dev"
Requires-Dist: flake8>=6.1.0; extra == "dev"
Requires-Dist: mypy>=1.7.0; extra == "dev"
Requires-Dist: pylint>=3.0.2; extra == "dev"
Requires-Dist: redis>=5.0.1; extra == "dev"
Requires-Dist: types-redis; extra == "dev"
Requires-Dist: types-setuptools; extra == "dev"
Requires-Dist: build; extra == "dev"
Requires-Dist: twine; extra == "dev"
Provides-Extra: redis
Requires-Dist: redis>=5.0.1; extra == "redis"
Dynamic: author
Dynamic: home-page
Dynamic: license-file
Dynamic: requires-python
